FinnSyll-2.0.0.dist-info/DESCRIPTION.rst
FinnSyll-2.0.0.dist-info/METADATA
FinnSyll-2.0.0.dist-info/RECORD
FinnSyll-2.0.0.dist-info/WHEEL
FinnSyll-2.0.0.dist-info/metadata.json
FinnSyll-2.0.0.dist-info/top_level.txt
finnsyll/__init__.py
finnsyll/phonology.py
finnsyll/syllabifier.py
finnsyll/utilities.py
finnsyll/v01.py
finnsyll/v02.py
finnsyll/v03.py
finnsyll/v04.py
finnsyll/v05.py
finnsyll/v06.py
finnsyll/v07.py
finnsyll/v08.py
finnsyll/v09.py
finnsyll/v1.py
finnsyll/v10.py
finnsyll/v11.py
finnsyll/v12.py
finnsyll/v13.py
finnsyll/v2.py
finnsyll/v3.py
finnsyll/v4.py
finnsyll/v5.py
finnsyll/v6.py
finnsyll/v7.py
finnsyll/v8.py
finnsyll/v9.py
finnsyll/data/.DS_Store
finnsyll/data/__init__.py
finnsyll/data/finnsyll-morfessor.bin
finnsyll/data/finnsyll-ngrams.pickle
finnsyll/data/finnsyll-training.txt
