Metadata-Version: 2.0
Name: FinnSyll
Version: 2.0.0
Summary: Finnish syllabifier and compound segmenter
Home-page: https://github.com/tsnaomi/finnsyll
Author: Naomi Tachikawa Shapiro
Author-email: coder@tsnaomi.net
License: BSD
Keywords: Finnish syllabifier compound segmenter
Platform: UNKNOWN
Classifier: Development Status :: 5 - Production/Stable
Classifier: Intended Audience :: Science/Research
Classifier: Topic :: Scientific/Engineering
Classifier: License :: OSI Approved :: BSD License
Classifier: Programming Language :: Python
Requires-Dist: morfessor
